{
  "Id": "VELDsAlterraWeaponry",
  "DisplayName": "Alterra® Weaponry™ (Subnautica Port)",
  "Author": "VELD (Original) | Community Port",
  "Version": "1.0.5",
  "Dependencies": [],
  "VersionDependencies": {
    "SMLHelper": "2.14.1"
  },
  "LoadBefore": [],
  "LoadAfter": [],
  "Enable": true,
  "Game": "Subnautica",
  "AssemblyName": "AlterraWeaponry.dll",
  "NitroxCompat": true,
  "VersionChecker": {
    "LatestVersionURL": "https://raw.githubusercontent.com/VELD-Dev/AlterraWeaponry/master/mod.json"
  }
}